abstract_bots/__init__.py
abstract_bots/abstract_bots.py
abstract_bots/abstract_keypair.py
abstract_bots/abstract_logs.py
abstract_bots/abstract_rpc_db .py
abstract_bots/abstract_rpc_db.py
abstract_bots/abstract_rpcs.py
abstract_bots/abstract_swap.py
abstract_bots/abstract_swaps.py
abstract_bots/abstract_transactions.py
abstract_bots/address_lookup.py
abstract_bots/bot_functions.py
abstract_bots/price_functions.py
abstract_bots/price_functions2.py
abstract_bots/pumpFunKeys.py
abstract_bots/pump_fun_swap.py
abstract_bots/raydium_pool_keys.py
abstract_bots/rpc.py
abstract_bots/solana_client_manager.py
abstract_bots/testTransaction.py
abstract_bots/txn_functions.py
abstract_bots/utils.py
abstract_bots/classes/__init__.py
abstract_bots/classes/abstractAccountKeysManager.py
abstract_bots/classes/abstractInstructionManager.py
abstract_bots/classes/abstractLogMessages.py
abstract_bots/classes/abstractTransactionProcessor.py
abstract_bots/classes/abstractTxnManager.py
abstract_bots/price_funcs/__init__.py
abstract_bots/price_funcs/price_functions.py
abstract_bots/pump_fun/__init__.py
abstract_bots/pump_fun/account_utils.py
abstract_bots/pump_fun/buyit.py
abstract_bots/pump_fun/coin_data.py
abstract_bots/pump_fun/constants.py
abstract_bots/pump_fun/flaSKIT.py
abstract_bots/pump_fun/instruction_utils.py
abstract_bots/pump_fun/isolated_rpcs.py
abstract_bots/pump_fun/pump_fun.py
abstract_bots/pump_fun/swap_utils.py
abstract_bots/pump_fun/txn_utils.py
abstract_bots/pump_fun/utils.py
abstract_bots/pumpit/__init__.py
abstract_bots/pumpit/account_utils.py
abstract_bots/pumpit/buy.py
abstract_bots/pumpit/buyit.py
abstract_bots/pumpit/coin_data.py
abstract_bots/pumpit/constants.py
abstract_bots/pumpit/isolated_rpcs.py
abstract_bots/pumpit/pump_fun.py
abstract_bots/pumpit/sell.py
abstract_bots/pumpit/utils.py
abstract_bots/solana_swaps/__init__.py
abstract_bots/solana_swaps/abstract_logs.py
abstract_bots/solana_swaps/abstract_swap.py
abstract_bots-0.0.1.57.dist-info/METADATA
abstract_bots-0.0.1.57.dist-info/WHEEL
abstract_bots-0.0.1.57.dist-info/top_level.txt
abstract_bots-0.0.1.57.dist-info/RECORD
