Metadata-Version: 2.1
Name: abstract_bots
Version: 0.0.1.57
Summary: This suite of modules not only simplifies the complexities associated with blockchain application development but also ensures high levels of performance and security. By providing tools for detailed data handling, transaction analysis, and secure blockchain interactions, these modules form a comprehensive solution ideal for developers looking to build or maintain advanced Solana-based applications.
Home-page: https://github.com/AbstractEndeavors/abstract_ai
Author: putkoff
Author-email: partners@abstractendeavors.com
Classifier: Development Status :: 3 - Alpha
Classifier: Intended Audience :: Developers
Classifier: License :: OSI Approved :: MIT License
Classifier: Programming Language :: Python :: 3
Classifier: Programming Language :: Python :: 3.11
Requires-Python: >=3.6
Requires-Dist: requests
Requires-Dist: solders
Requires-Dist: solana
Requires-Dist: base58
Requires-Dist: sqlalchemy
Requires-Dist: abstract_security
Requires-Dist: python-dotenv
Requires-Dist: abstract_utilities
